epubcat/__about__.py
epubcat/__init__.py
epubcat/__main__.py
epubcat-0.1.0.dist-info/METADATA
epubcat-0.1.0.dist-info/WHEEL
epubcat-0.1.0.dist-info/entry_points.txt
epubcat-0.1.0.dist-info/licenses/LICENSE.txt
epubcat-0.1.0.dist-info/RECORD
