Metadata-Version: 2.3
Name: epubcat
Version: 0.1.0
Project-URL: Documentation, https://github.com/zamu-flowerpot/epubcat#readme
Project-URL: Issues, https://github.com/zamu-flowerpot/epubcat/issues
Project-URL: Source, https://github.com/zamu-flowerpot/epubcat
Author-email: zamubafoo <106848396+zamu-flowerpot@users.noreply.github.com>
License-Expression: MIT
License-File: LICENSE.txt
Classifier: Development Status :: 4 - Beta
Classifier: Programming Language :: Python
Classifier: Programming Language :: Python :: 3.8
Classifier: Programming Language :: Python :: 3.9
Classifier: Programming Language :: Python :: 3.10
Classifier: Programming Language :: Python :: 3.11
Classifier: Programming Language :: Python :: 3.12
Classifier: Programming Language :: Python :: Implementation :: CPython
Classifier: Programming Language :: Python :: Implementation :: PyPy
Requires-Python: >=3.12
Requires-Dist: cssselect
Requires-Dist: ebooklib
Requires-Dist: ftfy
Requires-Dist: lxml
